odoo_log_parser/__init__.py
odoo_log_parser/cli.py
odoo_log_parser/echo_mode.py
odoo_log_parser/odoo_test_digest.py
odoo_log_parser/python_log_parser.py
jerproodoologparser-0.1.0.dist-info/METADATA
jerproodoologparser-0.1.0.dist-info/WHEEL
jerproodoologparser-0.1.0.dist-info/entry_points.txt
jerproodoologparser-0.1.0.dist-info/top_level.txt
jerproodoologparser-0.1.0.dist-info/RECORD
