Metadata-Version: 2.4
Name: JerProOdooLogParser
Version: 0.1.0
Summary: A library for parsing Odoo logs and collecting test information.
Author-email: João Jerónimo <joao.jeronimo.pro@gmail.com>
Classifier: Development Status :: 5 - Production/Stable
Requires-Python: >=3.7
